{
  "start_url": "https://dl.acm.org/",
  "query_words": [
    "find",
    "articles",
    "on",
    "neural networks",
    "sort by",
    "citation count"
  ],
  "query_annotations": [
    "",
    "",
    "",
    "topic",
    "",
    "key"
  ],
  "demonstration": [
    "input_text #neural networks# @ id(\"header\")/table[1]/tbody[1]/tr[2]/td[3]/table[1]/tbody[1]/tr[1]/td[1]/form[1]/span[1]/label[1]/input[1] || /html[1]/body[1]/div[2]/div[1]/table[1]/tbody[1]/tr[2]/td[3]/table[1]/tbody[1]/tr[1]/td[1]/form[1]/span[1]/label[1]/input[1]",
    "press_enter ## @ id(\"header\")/table[1]/tbody[1]/tr[2]/td[3]/table[1]/tbody[1]/tr[1]/td[1]/form[1]/span[1]/label[1]/input[1] || /html[1]/body[1]/div[2]/div[1]/table[1]/tbody[1]/tr[2]/td[3]/table[1]/tbody[1]/tr[1]/td[1]/form[1]/span[1]/label[1]/input[1]",
    "select #2# @ id(\"sortmenu\")/select[1] || /html[1]/body[1]/div[3]/div[4]/div[3]/div[1]/select[1]"
  ],
  "target_text_res": [],
  "target_url_res": [
    "query=neural%20networks",
    "srt=citedCount"
  ],
  "target_url": "https://dl.acm.org/results.cfm?query=neural%20networks&filtered=&within=owners%2Eowner%3DHOSTED&dte=&bfr=&srt=citedCount",
  "replayable": true
}